nbed/__init__.py
nbed/config.py
nbed/driver.py
nbed/embed.py
nbed/exceptions.py
nbed/ham_builder.py
nbed/nbedtypes.py
nbed/py.typed
nbed/utils.py
nbed/localizers/__init__.py
nbed/localizers/ace.py
nbed/localizers/system.py
nbed/localizers/occupied/__init__.py
nbed/localizers/occupied/base.py
nbed/localizers/occupied/pyscf.py
nbed/localizers/occupied/spade.py
nbed/localizers/virtual/__init__.py
nbed/localizers/virtual/base.py
nbed/localizers/virtual/concentric.py
nbed/localizers/virtual/projected_atomic.py
nbed/scf/__init__.py
nbed/scf/embedded_hcore_funcs.py
nbed/scf/huzinaga_scf.py
nbed-0.0.10.dist-info/METADATA
nbed-0.0.10.dist-info/WHEEL
nbed-0.0.10.dist-info/entry_points.txt
nbed-0.0.10.dist-info/licenses/LICENSE.md
nbed-0.0.10.dist-info/RECORD
