Metadata-Version: 2.4
Name: nbed
Version: 0.0.10
Summary: Projection-based embedding methods for reducing quantum simulation resource requirements.
Author-email: Michael Williams de la Bastida <michael.williams.20@ucl.ac.uk>, Alexis Ralli <alexis.ralli.18@ucl.ac.uk>
License-File: LICENSE.md
Requires-Python: <4,>=3.12
Requires-Dist: numpy>=2.3.0
Requires-Dist: openfermion<2.0.0,>=1.1.0
Requires-Dist: pydantic>=2.11.7
Requires-Dist: pyscf<3.0.0,>=2.3.0
Requires-Dist: pytest-xdist>=3.8.0
Requires-Dist: pyyaml<7.0.0,>=6.0.0
Requires-Dist: qiskit-nature<1.0.0,>=0.7.0
